asyncpushbullet/__init__.py
asyncpushbullet/__version__.py
asyncpushbullet/_compat.py
asyncpushbullet/async_listeners.py
asyncpushbullet/async_pushbullet.py
asyncpushbullet/channel.py
asyncpushbullet/chat.py
asyncpushbullet/command_line_listen.py
asyncpushbullet/command_line_push.py
asyncpushbullet/device.py
asyncpushbullet/ephemeral_comm.py
asyncpushbullet/errors.py
asyncpushbullet/filetype.py
asyncpushbullet/helpers.py
asyncpushbullet/listener.py
asyncpushbullet/oauth2.py
asyncpushbullet/prefs.py
asyncpushbullet/pushbullet.py
asyncpushbullet/subscription.py
asyncpushbullet/tqio.py
asyncpushbullet/websocket_client.py
asyncpushbullet/websocket_server.py
asyncpushbullet-0.18.11.dist-info/LICENSE
asyncpushbullet-0.18.11.dist-info/METADATA
asyncpushbullet-0.18.11.dist-info/WHEEL
asyncpushbullet-0.18.11.dist-info/entry_points.txt
asyncpushbullet-0.18.11.dist-info/top_level.txt
asyncpushbullet-0.18.11.dist-info/RECORD
