Metadata-Version: 2.1
Name: asyncpushbullet
Version: 0.18.11
Summary: A synchronous and asyncio-based client for pushbullet.com
Home-page: https://github.com/rharder/asyncpushbullet
Author: Robert Harder, Richard Borcsik
Author-email: rob@iharder.net, borcsikrichard@gmail.com
License: MIT
Download-URL: https://github.com/rharder/asyncpushbullet/tarball/0.18.11
Keywords: push android pushbullet notification
Platform: UNKNOWN
Classifier: Development Status :: 4 - Beta
Classifier: Intended Audience :: Developers
Classifier: Programming Language :: Python
Classifier: Natural Language :: English
Classifier: License :: OSI Approved :: MIT License
Classifier: Programming Language :: Python :: 3
Classifier: Programming Language :: Python :: 3.6
Classifier: Programming Language :: Python :: 3.7
Classifier: Topic :: Software Development :: Libraries :: Python Modules
Classifier: Topic :: Utilities
Requires-Dist: requests
Requires-Dist: python-magic
Requires-Dist: aiohttp
Requires-Dist: tqdm
Requires-Dist: appdirs
Provides-Extra: gui
Requires-Dist: pillow ; extra == 'gui'
